{
  "facebook": {
    "100051721170298": {
      "reason": "https://imgur.com/TKsAoBo.png",
      "noAdding": true
    },
    "100034738337866": {
      "reason": "Dùng theo kiểu không dùng được thì vứt, kick ra?",
      "noAdding": true
    },
    "100007940561404": {
      "reason": "https://i.imgur.com/3hFx7tT.png",
      "noAdding": true
    },
    "100039641953856": {
      "reason": "https://i.imgur.com/1hzHv9S.png",
      "noAdding": true
    },
    "3343956622300706": {
      "reason": "3 thằng bot"
    },
    "1742436175856017": {
      "reason": "add làm đéo gì nhiều bot thế?"
    },
    "100027697060977": {
      "reason": "không thích dùng thì cút",
      "noAdding": true
    },
    "2145904258846806": {
      "reason": "nhiều bot làm gì vậy cái group này?"
    },
    "100040468722739": {
      "reason": "\"2 con của em thêm\"",
      "noAdding": true
    },
    "100013238112840": {
      "reason": "không biết dùng togglethanos thì thôi ban luôn cho nhanh",
      "noAdding": true
    },
    "2635401416555279": {
      "reason": "bye"
    },
    "100029514863791": {
      "reason": "kick ra thì bye",
      "noAdding": true
    },
    "100017916917432": {
      "reason": "kick ra thì bye luôn lmao, đi mà làm nhạc trên FL Studio Mobile ý :))",
      "noAdding": true
    },
    "100047203404355": {
      "reason": "dính ban wave vì thiểu năng",
      "noAdding": true
    },
    "100046029799897": {
      "reason": "dính ban wave vì thiểu năng",
      "noAdding": true
    },
    "100029747958558": {
      "reason": "dính ban wave vì thiểu năng",
      "noAdding": true
    },
    "100024406657711": {
      "reason": "dính ban wave vì thiểu năng",
      "noAdding": true
    },
    "100047890927695": {
      "reason": "dính ban wave vì thiểu năng",
      "noAdding": true
    },
    "100043780878565": {
      "reason": "dính ban wave vì thiểu năng",
      "noAdding": true
    },
    "100007143185234": {
      "reason": "dính ban wave vì thiểu năng",
      "noAdding": true
    },
    "100049339567542": {
      "reason": "dính ban wave vì thiểu năng",
      "noAdding": true
    },
    "100036161863352": {
      "reason": "dính ban wave vì thiểu năng",
      "noAdding": true
    },
    "100034292363249": {
      "reason": "dính ban wave vì thiểu năng",
      "noAdding": true
    },
    "100035623611618": {
      "reason": "dính ban wave vì thiểu năng",
      "noAdding": true
    },
    "100022014451463": {
      "reason": "dính ban wave vì thiểu năng",
      "noAdding": true
    },
    "100045609000903": {
      "reason": "dính ban wave vì thiểu năng",
      "noAdding": true
    },
    "100047127877107": {
      "reason": "dính ban wave vì thiểu năng",
      "noAdding": true
    },
    "100040026608669": {
      "reason": "dính ban wave vì thiểu năng",
      "noAdding": true
    },
    "100030541659789": {
      "reason": "dính ban wave vì thiểu năng",
      "noAdding": true
    },
    "100014616724849": {
      "reason": "dính ban wave vì lọc mem",
      "noAdding": true
    },
    "100008420028755": {
      "reason": "dính ban wave vì \"You can't reply to this conversation.\"",
      "noAdding": true
    },
    "100045135691723": {
      "reason": "https://i.imgur.com/FxlabhS.png",
      "noAdding": true
    },
    "100023067930145": {
      "reason": "spam nhiều? giả bot? đây là bot thật mà. https://i.imgur.com/Eno5zoz.jpg",
      "noAdding": true
    },
    "100040265525218": {
      "reason": "đóng tiền bảo kê 50k cc",
      "noAdding": true
    },
    "100022487149660": {
      "reason": "doạ trẻ em? https://i.imgur.com/lIpZQae.png",
      "noAdding": true
    },
    "100006833808486": {
      "reason": "nÓ cHỉ TíNh LeVeL tHôI. https://i.imgur.com/2bRyCmh.png",
      "noAdding": true
    },
    "100017442096717": {
      "reason": "dính ban wave đợt 2, ngu l",
      "noAdding": true
    },
    "100023900152717": {
      "reason": "dính ban wave đợt 2, ngu l",
      "noAdding": true
    },
    "100041682534210": {
      "reason": "dính ban wave đợt 2, ngu l",
      "noAdding": true
    },
    "100004666368666": {
      "reason": "dính ban wave đợt 2, ngu l",
      "noAdding": true
    },
    "100027413042190": {
      "reason": "dính ban wave đợt 2, ngu l",
      "noAdding": true
    },
    "100037863321974": {
      "reason": "dính ban wave đợt 2, ngu l",
      "noAdding": true
    },
    "100045592397067": {
      "reason": "dính ban wave đợt 2, ngu l",
      "noAdding": true
    },
    "100036449568467": {
      "reason": "dính ban wave đợt 2, ngu l",
      "noAdding": true
    },
    "100014637887497": {
      "reason": "dính ban wave đợt 2, ngu l",
      "noAdding": true
    },
    "100049689485408": {
      "reason": "dính ban wave đợt 2, ngu l",
      "noAdding": true
    },
    "100014741910502": {
      "reason": "dính ban wave đợt 2, ngu l",
      "noAdding": true
    },
    "100009705345655": {
      "reason": "dính ban wave đợt 2, ngu l",
      "noAdding": true
    },
    "100024169188138": {
      "reason": "dính ban wave đợt 2, ngu l",
      "noAdding": true
    },
    "100049167693633": {
      "reason": "dính ban wave đợt 2, ngu l",
      "noAdding": true
    },
    "100028440723020": {
      "reason": "dính ban wave đợt 2, ngu l",
      "noAdding": true
    },
    "100037626262843": {
      "reason": "dính ban wave đợt 2, ngu l",
      "noAdding": true
    },
    "100040245785129": {
      "reason": "dính ban wave đợt 2, ngu l",
      "noAdding": true
    },
    "100048078740360": {
      "reason": "dính ban wave đợt 2, ngu l",
      "noAdding": true
    },
    "100008093490842": {
      "reason": "dính ban wave đợt 2, ngu l",
      "noAdding": true
    },
    "100028978184480": {
      "reason": "dính ban wave đợt 2, ngu l",
      "noAdding": true
    },
    "100035013763118": {
      "reason": "dính ban wave đợt 2, ngu l",
      "noAdding": true
    },
    "100013396096928": {
      "reason": "dính ban wave đợt 2, ngu l",
      "noAdding": true
    },
    "100038693852109": {
      "reason": "dính ban wave đợt 2, ngu l",
      "noAdding": true
    },
    "100011284476463": {
      "reason": "dính ban wave đợt 2, ngu l",
      "noAdding": true
    },
    "100047906989161": {
      "reason": "dính ban wave đợt 2, ngu l",
      "noAdding": true
    },
    "100009470417316": {
      "reason": "dính ban wave đợt 2, ngu l",
      "noAdding": true
    },
    "100016009487520": {
      "reason": "dính ban wave đợt 2, ngu l",
      "noAdding": true
    },
    "100013738742922": {
      "reason": "dính ban wave đợt 2, ngu l",
      "noAdding": true
    },
    "100037788337570": {
      "reason": "dính ban wave đợt 2, ngu l",
      "noAdding": true
    },
    "100037479832610": {
      "reason": "dính ban wave đợt 2, ngu l",
      "noAdding": true
    },
    "100025533312695": {
      "reason": "dính ban wave đợt 2, ngu l",
      "noAdding": true
    },
    "100035257832603": {
      "reason": "dính ban wave đợt 2, ngu l",
      "noAdding": true
    },
    "100048326962894": {
      "reason": "dính ban wave đợt 2, ngu l",
      "noAdding": true
    },
    "100039491989266": {
      "reason": "dính ban wave đợt 2, ngu l",
      "noAdding": true
    },
    "100039099935985": {
      "reason": "https://i.imgur.com/RTPWbPc.png",
      "noAdding": true
    },
    "100050108285641": {
      "reason": "thiểu năng vừa vừa thôi. https://www.facebook.com/groups/c3cbot/permalink/227203071884770/",
      "noAdding": true
    },
    "100023548170929": {
      "reason": "Ban wave / Ep. 03 / Kick bừa, phá, ...",
      "noAdding": true
    },
    "100048020393129": {
      "reason": "Ban wave / Ep. 03 / Kick bừa, phá, ...",
      "noAdding": true
    },
    "100049023916304": {
      "reason": "Ban wave / Ep. 03 / Kick bừa, phá, ...",
      "noAdding": true
    },
    "100050557452223": {
      "reason": "Ban wave / Ep. 03 / Kick bừa, phá, ...",
      "noAdding": true
    },
    "100010133024065": {
      "reason": "Ban wave / Ep. 03 / Kick bừa, phá, ...",
      "noAdding": true
    },
    "100035744737916": {
      "reason": "Ban wave / Ep. 03 / Kick bừa, phá, ...",
      "noAdding": true
    },
    "100036619911126": {
      "reason": "Ban wave / Ep. 03 / Kick bừa, phá, ...",
      "noAdding": true
    },
    "100030189562072": {
      "reason": "Ban wave / Ep. 03 / Kick bừa, phá, ...",
      "noAdding": true
    },
    "100024682270418": {
      "reason": "Ban wave / Ep. 03 / Kick bừa, phá, ...",
      "noAdding": true
    },
    "100017567829768": {
      "reason": "Ban wave / Ep. 03 / Kick bừa, phá, ...",
      "noAdding": true
    },
    "100024379117098": {
      "reason": "Ban wave / Ep. 03 / Kick bừa, phá, ...",
      "noAdding": true
    },
    "100008044337536": {
      "reason": "Ban wave / Ep. 03 / Kick bừa, phá, ...",
      "noAdding": true
    },
    "100038051259249": {
      "reason": "Ban wave / Ep. 03 / Kick bừa, phá, ...",
      "noAdding": true
    },
    "100046188663719": {
      "reason": "Ban wave / Ep. 03 / Kick bừa, phá, ...",
      "noAdding": true
    },
    "100047254365686": {
      "reason": "bạn khoá acc luôn thì ghê rồi, nhưng mình nhìn sâu vào code hơn :)) | wave 3 hit",
      "noAdding": true
    },
    "100007143900486": {
      "reason": "Ban wave / Ep. 03 / Kick bừa, phá, ...",
      "noAdding": true
    },
    "100003184726261": {
      "reason": "Ban wave / Ep. 03 / Kick bừa, phá, ...",
      "noAdding": true
    },
    "100030991635988": {
      "reason": "Ban wave / Ep. 03 / Kick bừa, phá, ...",
      "noAdding": true
    },
    "100014254455526": {
      "reason": "Ban wave / Ep. 03 / Kick bừa, phá, ...",
      "noAdding": true
    },
    "100031286234512": {
      "reason": "Ban wave / Ep. 03 / Kick bừa, phá, ...",
      "noAdding": true
    },
    "100035106194096": {
      "reason": "Ban wave / Ep. 03 / Kick bừa, phá, ...",
      "noAdding": true
    },
    "100038138421248": {
      "reason": "Ban wave / Ep. 03 / Kick bừa, phá, ...",
      "noAdding": true
    },
    "100014841002929": {
      "reason": "Ban wave / Ep. 03 / Kick bừa, phá, ...",
      "noAdding": true
    },
    "100031290601150": {
      "reason": "Ban wave / Ep. 03 / Kick bừa, phá, ...",
      "noAdding": true
    },
    "100021527709035": {
      "reason": "Ban wave / Ep. 03 / Kick bừa, phá, ...",
      "noAdding": true
    },
    "100015879581000": {
      "reason": "Ban wave / Ep. 03 / Kick bừa, phá, ...",
      "noAdding": true
    },
    "100017626143638": {
      "reason": "Ban wave / Ep. 03 / Kick bừa, phá, ...",
      "noAdding": true
    },
    "100050506418657": {
      "reason": "Ban wave / Ep. 03 / Kick bừa, phá, ...",
      "noAdding": true
    },
    "100027016878281": {
      "reason": "Ban wave / Ep. 03 / Kick bừa, phá, ...",
      "noAdding": true
    },
    "100031973791160": {
      "reason": "Ban wave / Ep. 03 / Kick bừa, phá, ...",
      "noAdding": true
    },
    "100041664054053": {
      "reason": "Ban wave / Ep. 03 / Kick bừa, phá, ...",
      "noAdding": true
    },
    "100024252360517": {
      "reason": "Ban wave / Ep. 03 / Kick bừa, phá, ...",
      "noAdding": true
    },
    "100018624949282": {
      "reason": "Ban wave / Ep. 03 / Kick bừa, phá, ...",
      "noAdding": true
    },
    "100033263255328": {
      "reason": "Ban wave / Ep. 03 / Kick bừa, phá, ...",
      "noAdding": true
    },
    "100028114535455": {
      "reason": "Ban wave / Ep. 03 / Kick bừa, phá, ...",
      "noAdding": true
    },
    "100035272114042": {
      "reason": "bạn khoá acc luôn thì ghê rồi, nhưng mình nhìn sâu vào code hơn :)) | wave 3 hit",
      "noAdding": true
    },
    "100014622517112": {
      "reason": "Ban wave / Ep. 03 / Kick bừa, phá, ...",
      "noAdding": true
    },
    "100012322305152": {
      "reason": "Ban wave / Ep. 03 / Kick bừa, phá, ...",
      "noAdding": true
    },
    "100016930932410": {
      "reason": "Ban wave / Ep. 03 / Kick bừa, phá, ...",
      "noAdding": true
    },
    "100023370462233": {
      "reason": "Ban wave / Ep. 03 / Kick bừa, phá, ...",
      "noAdding": true
    },
    "100011500894348": {
      "reason": "Ban wave / Ep. 03 / Kick bừa, phá, ...",
      "noAdding": true
    },
    "100034817528858": {
      "reason": "Ban wave / Ep. 03 / Kick bừa, phá, ...",
      "noAdding": true
    },
    "100012422087234": {
      "reason": "Ban wave / Ep. 03 / Kick bừa, phá, ...",
      "noAdding": true
    },
    "100025910925845": {
      "reason": "Ban wave / Ep. 03 / Kick bừa, phá, ...",
      "noAdding": true
    },
    "100048177530185": {
      "reason": "Ban wave / Ep. 03 / Kick bừa, phá, ...",
      "noAdding": true
    },
    "100036764018062": {
      "reason": "bị ban rồi, kick/add làm gì :)) https://tinyurl.com/y88tkyge",
      "noAdding": true
    },
    "100012258552932": {
      "reason": "bị ban vì ăn cắp source code. developer chính: https://fb.me/lql.uiri",
      "noAdding": true
    },
    "100016533481952": {
      "reason": "kick/add bot liên tục. https://imgur.com/a/lG3IqXe (reported by https://fb.com/100046054221757)",
      "noAdding": true
    },
    "100041140590784": {
      "reason": "add 2 bot trong cùng 1 box. https://imgur.com/a/y7ptuVa (reported by https://fb.com/100046054221757)",
      "noAdding": true
    },
    "100049173382500": {
      "reason": "add 2 bot trong cùng 1 box. https://imgur.com/a/dpDyZxc (reported by https://fb.com/100046054221757)",
      "noAdding": true
    },
    "100028386665513": {
      "reason": "vcl đây là bot thật alo. https://imgur.com/a/I0cHT1z (reported by https:/fb.com/100037997250555)",
      "noAdding": true
    },
    "2982768651807437": {
      "reason": "à vâng nhạt nhưng không cần vô phá. https://i.imgur.com/IgIa9oT.png"
    },
    "100033808193961": {
      "reason": "oh well, bot được lập trình sẵn vậy mà. không muốn dùng thanos? `/thanos off`. đơn giản, nhưng ăn ban rồi :)) (reported by https://fb.com/100048217848970) | https://i.imgur.com/PgXRNic.png https://i.imgur.com/6EjFcFh.png https://i.imgur.com/RGL2u2Q.png",
      "noAdding": true
    },
    "2961457267244044": {
      "reason": "hoạt động ở rất rất nhiều nhóm chứ không chỉ có mỗi hai nhóm đâu? https://tinyurl.com/y8qyp4jd https://tinyurl.com/y7zgp8sq"
    },
    "100028127678026": {
      "reason": "hoạt động ở rất rất nhiều nhóm chứ không chỉ có mỗi hai nhóm đâu? https://tinyurl.com/y8qyp4jd https://tinyurl.com/y7zgp8sq",
      "noAdding": true
    },
    "100035210281031": {
      "reason": "vote hùa lmao https://tinyurl.com/y8qyp4jd https://tinyurl.com/y7zgp8sq",
      "noAdding": true
    },
    "100046699808878": {
      "reason": "vote hùa lmao https://tinyurl.com/y8qyp4jd https://tinyurl.com/y7zgp8sq",
      "noAdding": true
    },
    "100024504762306": {
      "reason": "rất mát, cảm ơn. https://tinyurl.com/y7ukhesc",
      "noAdding": true
    },
    "3146661212023357": {
      "reason": "cùng 1 source thì lại chả giống nhau? rất mát. https://tinyurl.com/ybkt2evl [à còn nữa, dùng nhiều bot trong 1 box à nha :))]"
    },
    "2814330555341820": {
      "reason": "hít hà, offline thì báo admin, chứ ngồi đó mà kick :)) https://tinyurl.com/ycf5kdvx [à đúng rồi, Lê Bảo Long là hàng chính thức chứ ngồi đó mà fake :))]"
    },
    "2928667800560502": {
      "reason": "rất mát, dùng luôn cả 2 bot nhỉ? https://tinyurl.com/yajjvryl"
    },
    "2379906362085980": {
      "reason": "mát thế, dùng Bé Tư xong add thêm Bảo Long vào. https://tinyurl.com/yaungqov"
    },
    "100022438811248": {
      "reason": "không có hệ thống nào là hoàn hảo, cả bot cũng vậy. https://i.imgur.com/hGMttKR.png",
      "noAdding": true
    },
    "100028727385464": {
      "reason": "nghịch cho đã rồi đổi bot liên tục :)) https://imgur.com/a/BVoSx04",
      "noAdding": true
    },
    "100006633371718": {
      "reason": "nếu như không muốn dùng Thanos, chỉ việc dùng lệnh `#thanos off` là được rồi mà ta hmm... https://i.imgur.com/7VD7iLG.png",
      "noAdding": true
    },
    "100049317841011": {
      "reason": "thế giờ phải làm thế nào mới vừa lòng :| https://i.imgur.com/0msVUQT.png",
      "noAdding": true
    },
    "100021956293070": {
      "reason": "à thì phải có người thêm mới vào được chứ? btw đú đảng vừa thôi. https://imgur.com/a/HYLy4e6",
      "noAdding": true
    },
    "100010568624269": {
      "reason": "à thì bị ping tức quá kick luôn à :)) thôi thì ăn ban để không bị ping everyone nữa nhé. https://i.imgur.com/m90swxa.png",
      "noAdding": true
    },
    "100024605084255": {
      "reason": "yep vô dụng lắm (reported by https://fb.com/100048217848970) | https://i.imgur.com/HDWNZRg.png",
      "noAdding": true
    },
    "100049360488633": {
      "reason": "lựa đúng lúc MQTT bị lỗi mà bảo nhầm người, hơn nữa đâu phải add vào là chạy ngay nhỉ 🤔 (reported by https://fb.com/100048217848970) | https://i.imgur.com/VwGDgaZ.png",
      "noAdding": true
    },
    "100051405499576": {
      "reason": "j nghe người khác xong kick (reported by https://fb.com/100048217848970) | https://i.imgur.com/is5Gm00.png",
      "noAdding": true
    },
    "100049589460941": {
      "reason": "j 2 acc 1 chủ? làm gì có? cả việc nếu k muốn dùng thanos thì làm mẹ quả `/thanos off` đi. (reported by https://fb.com/100048217848970) | https://i.imgur.com/XDwcZ31.png https://i.imgur.com/37fLYhf.png",
      "noAdding": true
    },
    "100024769242264": {
      "reason": "j không gỡ được admin xong kick? (reported by https://fb.com/100048217848970) | https://i.imgur.com/aVZGQqG.png",
      "noAdding": true
    },
    "100051851105294": {
      "reason": "bot câm, trừ khi có người động :) (reported by https://fb.com/100048217848970) | https://i.imgur.com/LRPDfe5.png",
      "noAdding": true
    },
    "100050457338284": {
      "reason": "j nghe bảo lọc bot ra k báo trước (reported by https://fb.com/100048217848970) | https://i.imgur.com/HhitYIN.png",
      "noAdding": true
    },
    "100049859632634": {
      "reason": "j xúi người khác lọc bot ra (reported by https://fb.com/100048217848970) | https://i.imgur.com/HhitYIN.png",
      "noAdding": true
    },
    "100049700670422": {
      "reason": "well bot không thể định vị, trừ khi bạn cung cấp toạ độ cho việc tra cứu thời tiết (và chả ai thèm gì vị trí đó cả). à đúng rồi cả quả 'kick cho em mình fix' hay đấy, bot có phải của bạn đâu? (reported by https://fb.com/100048217848970) | https://i.imgur.com/KbxBTL4.png https://i.imgur.com/hSNBzHS.png",
      "noAdding": true
    },
    "100024226746932": {
      "reason": "nghe nói bạn kick bot ra nhỉ? bot lâu lâu bị lỗi MQTT, đâu phải thứ gì cũng hoàn hảo đâu nhỉ. (reported by https://fb.com/100048217848970) | https://i.imgur.com/vwT6J13.png",
      "noAdding": true
    },
    "100047797298101": {
      "reason": "'tôi đề nghị Trần Dy kick bot'. ừ cả hai ăn ban. (reported by https://fb.com/100048217848970) | https://i.imgur.com/vwT6J13.png",
      "noAdding": true
    },
    "100027357681286": {
      "reason": "oh well 'thôi không thích thì xoá'. (reported by https://fb.com/100048217848970) | https://i.imgur.com/aiWbJD0.png",
      "noAdding": true
    },
    "100001916405713": {
      "reason": "mình nghe nói bạn là người kick bot, nghe người khác bảo kick. (reported by https://fb.com/100048217848970) | https://i.imgur.com/aiWbJD0.png",
      "noAdding": true
    },
    "100045525095966": {
      "reason": "người khác xúi, bạn kick, bạn ăn ban. (reported by https://fb.com/100048217848970) | https://i.imgur.com/HDfsSzY.png",
      "noAdding": true
    },
    "100029670529351": {
      "reason": "lỗi có tí bên máy chủ xử lí mà đã kick bot rồi... (reported by https://fb.com/100048217848970) | https://i.imgur.com/bOGnY0p.png",
      "noAdding": true
    },
    "100026952582421": {
      "reason": "nghe người khác bảo kick, bạn kick, bạn ăn ban. (reported by https://fb.com/100048217848970) | https://i.imgur.com/uONKDGD.png",
      "noAdding": true
    },
    "100022448478495": {
      "reason": "mình ngửi thấy mùi dùng nhiều bot, nhưng không biết có phải không. (reported by https://fb.com/100048217848970) | https://i.imgur.com/uONKDGD.png",
      "noAdding": true
    },
    "100048260148748": {
      "reason": "không muốn dùng thanos? `/thanos off`. đơn giản, nhưng giờ thì ăn ban rồi. (reported by https://fb.com/100048217848970) | https://i.imgur.com/NpYEMSJ.png",
      "noAdding": true
    },
    "100043495869924": {
      "reason": "spam report (reported by https://fb.com/100009285954354) | https://imgur.com/a/LVc9bdw",
      "noAdding": true
    },
    "100051653052613": {
      "reason": "spam report (reported by https://fb.com/100009285954354) | https://imgur.com/a/LVc9bdw",
      "noAdding": true
    },
    "100047765739940": {
      "reason": "spam report (reported by https://fb.com/100009285954354) | https://imgur.com/a/LVc9bdw",
      "noAdding": true
    },
    "100023807556682": {
      "reason": "kick bừa này (captured by GopnikAK47) | https://i.imgur.com/8HQ8BA7.png",
      "noAdding": true
    },
    "100008972621116": {
      "reason": "spam report, nhờn (reported by https://fb.com/100009285954354) | https://imgur.com/a/7TfGt6E",
      "noAdding": true
    },
    "100028605142350": {
      "reason": "spam report, nhờn (reported by https://fb.com/100009285954354) | https://imgur.com/a/7TfGt6E",
      "noAdding": true
    },
    "100025274323582": {
      "reason": "spam report, nhờn (reported by https://fb.com/100009285954354) | https://imgur.com/a/7TfGt6E",
      "noAdding": true
    },
    "100015226789367": {
      "reason": "spam report, nhờn (reported by https://fb.com/100009285954354) | https://imgur.com/a/7TfGt6E",
      "noAdding": true
    },
    "100023528943008": {
      "reason": "spam report, nhờn (reported by https://fb.com/100009285954354) | https://imgur.com/a/7TfGt6E",
      "noAdding": true
    },
    "100009373699985": {
      "reason": "spam report, nhờn (reported by https://fb.com/100009285954354) | https://imgur.com/a/7TfGt6E",
      "noAdding": true
    },
    "100005414913988": {
      "reason": "spam report, nhờn (reported by https://fb.com/100009285954354) | https://imgur.com/a/7TfGt6E",
      "noAdding": true
    },
    "100052565801593": {
      "reason": "spam report, nhờn (reported by https://fb.com/100009285954354) | https://imgur.com/a/7TfGt6E",
      "noAdding": true
    },
    "100051964834842": {
      "reason": "spam report, nhờn (reported by https://fb.com/100009285954354) | https://imgur.com/a/7TfGt6E",
      "noAdding": true
    },
    "100044885072055": {
      "reason": "Bạn bảo mình tổn luồi, xin lỗi bạn tuổi lồn | https://imgur.com/a/95IgNvP",
      "noAdding": true
    },
    "100025036153712": {
      "reason": "spam phá bot, nhờn | https://imgur.com/a/6wc5WLf",
      "noAdding": true
    },
    "100016276776581": {
      "reason": "spam phá bot, nhờn | https://imgur.com/a/b10r83V",
      "noAdding": true
    },
    "100026526165732": {
      "reason": "spam phá bot, nhờn | https://imgur.com/a/b10r83V",
      "noAdding": true
    },
    "100009966315991": {
      "reason": "vừa ăn cắp vừa la làng vừa double bot. fine. rất mát. https://imgur.com/a/8nDulWw (reported by DUCK)",
      "noAdding": true
    },
    "100029305852775": {
      "reason": "kick con mẹ mày chứ kick. https://imgur.com/a/kN4rgJp",
      "noAdding": true
    },
    "100047462733697": {
      "reason": "kick con mẹ mày chứ kick. https://imgur.com/a/B8cVOY8",
      "noAdding": true
    },
    "100046032705492": {
      "reason": "không làm mà đòi có ăn. https://imgur.com/a/MCs4sQk",
      "noAdding": true
    },
    "100026974938223": {
      "reason": "spam à bạn? Cút. https://imgur.com/a/zpwmxVt",
      "noAdding": true
    },
    "3079000495502345": {
      "reason": "dùng 2 bot? https://tinyurl.com/y95cr4f8 https://tinyurl.com/ybl3jzzm"
    },
    "100045876008952": {
      "reason": "dùng 2 bot? https://tinyurl.com/y95cr4f8 https://tinyurl.com/ybl3jzzm",
      "noAdding": true
    },
    "2171629172848524": {
      "reason": "dùng 2 bot. https://tinyurl.com/yaky4tsk"
    },
    "2330598793697744": {
      "reason": "dùng 2 bot. https://tinyurl.com/ya7ph8yc"
    },
    "3830912403646614": {
      "reason": "ồ, đoán xem, bộ tưởng mình không bắt các bạn dùng 2 bot được à? https://tinyurl.com/y7sepap3"
    },
    "100044421527836": {
      "reason": "dùng 2 bot? Ban nhé bạn. | https://imgur.com/a/KhGlxcj",
      "noAdding": true
    },
    "100042532277860": {
      "reason": "dùng 2 bot? Ban nhé bạn. | https://imgur.com/a/wuGt8GY",
      "noAdding": true
    },
    "100041040186349": {
      "reason": "dùng 2 bot, thái độ lồi lõm, không hối lỗi. | https://imgur.com/a/9OmRXN1",
      "noAdding": true
    },
    "100032189101555": {
      "reason": "500s cơ mà, làm cái gì mà sồn sồn thế. Btw bên trên có sẵn bot rồi mà add em thứ 2 thì bạn cũng vi phạm luật nhé. | https://imgur.com/a/ruk3jVV",
      "noAdding": true
    },
    "100009406892911": {
      "reason": "500s cơ mà, làm cái gì mà sồn sồn thế. Chửi bot à bạn? Hay lắm, toàn bộ GULLS không có bot nhé. | https://imgur.com/a/vPJbk9i",
      "noAdding": true
    },
    "100025809122344": {
      "reason": "spam report với chúng tôi à | https://imgur.com/a/TckcvB5",
      "noAdding": true
    },
    "100044693113094": {
      "reason": "kick bot add liên tục | https://imgur.com/9Zq4nG8",
      "noAdding": true
    },
    "100050824482728": {
      "reason": "kick nhiều lần | https://imgur.com/aTyadY4",
      "noAdding": true
    },
    "100046886614581": {
      "reason": "đấm",
      "noAdding": false
    },
    "100037455795457": {
      "reason": "rối thì thêm làm gì ? | https://imgur.com/bdaBG0y",
      "noAdding": true
    },
    "100025496921350": {
      "reason": "spam report | https://imgur.com/a/TSj9wXh",
      "noAdding": true
    },
    "3208776915841591": {
      "reason": "kick con cặc, đéo biết chờ là gì à? | https://imgur.com/a/Tf98WYs"
    },
    "100021927992602": {
      "reason": "kick con cặc, đéo biết chờ là gì à? | https://imgur.com/a/Tf98WYs",
      "noAdding": true
    },
    "100027767712945": {
      "reason": "kick con cặc, đéo biết chờ là gì à? | https://imgur.com/a/Tf98WYs",
      "noAdding": true
    },
    "100043414924678": {
      "reason": "kick con cặc, đéo biết chờ là gì à? | https://imgur.com/a/Tf98WYs",
      "noAdding": true
    },
    "100025800883148": {
      "reason": "kick con cặc, đéo biết chờ là gì à? | https://imgur.com/a/Tf98WYs",
      "noAdding": true
    },
    "100042323991431": {
      "reason": "kick con cặc, đéo biết chờ là gì à? | https://imgur.com/a/Tf98WYs",
      "noAdding": true
    },
    "100039348253944": {
      "reason": "reported by TrickerT | https://imgur.com/a/yOQHNGZ, https://imgur.com/a/jTCfmXy",
      "noAdding": true
    },
    "100025460256974": {
      "reason": "reported by TrickerT | https://imgur.com/a/yOQHNGZ, https://imgur.com/a/jTCfmXy",
      "noAdding": true
    },
    "100022438451705": {
      "reason": "add 3 bot | https://imgur.com/IGzv7iH",
      "noAdding": true
    },
    "100052772690462": {
      "reason": "add 3 bot | https://imgur.com/IGzv7iH",
      "noAdding": true
    },
    "100028599102047": {
      "reason": "add 3 bot, add mẹ gì add lắm thế? | https://imgur.com/a/ZuQheIa, https://imgur.com/a/hzeU2xS, https://imgur.com/a/VXzBhMX",
      "noAdding": true
    },
    "100019265230205": {
      "reason": "spam lệnh, cảnh cáo nhưng vẫn nhờn | http://tiny.cc/p0jqsz",
      "noAdding": true
    },
    "100027187894903": {
      "reason": "add 2 bot 1 box, nhưng đằng này lại 2 box, mỗi box 2 bot, chửi admin là thằng, làm phiền,... | https://imgur.com/a/UW9C9Hr",
      "noAdding": true
    },
    "100044906144266": {
      "reason": "bot là rác? Xin lỗi, không. Bạn là rác. | https://imgur.com/a/hgOC6lk",
      "noAdding": true
    },
    "100054575792784": {
      "reason": "dùng 1 con bot thôi, có phải khi thu còn chưa tới là em thay bot mới đâu? Ít ra cũng phải báo chứ? | https://imgur.com/a/b9a0CHc",
      "noAdding": true
    },
    "100048299916912": {
      "reason": "tôi lại sợ bạn quá hmu hmu. | https://imgur.com/a/SATh4E9",
      "noAdding": true
    },
    "100032507552549": {
      "reason": "report nhảm <(")",
      "noAdding": true
    }
  },
  "discord": {}
}
